cubiscan/__init__.py
cubiscan/base_responses.py
cubiscan/command.py
cubiscan/cubiscan.py
cubiscan/helpers.py
cubiscan-0.0.3.dist-info/LICENCE
cubiscan-0.0.3.dist-info/METADATA
cubiscan-0.0.3.dist-info/WHEEL
cubiscan-0.0.3.dist-info/top_level.txt
cubiscan-0.0.3.dist-info/RECORD
