Metadata-Version: 1.1
Name: cubiscan
Version: 0.0.3
Summary: Library to talk to cubiscan machines
Home-page: https://github.com/camptocamp/cubiscan
Author: Camptocamp
Author-email: info@camptocamp.com
License: LGPLv3+
Platform: UNKNOWN
Classifier: Development Status :: 3 - Alpha
Classifier: Intended Audience :: Developers
Classifier: Natural Language :: English
Classifier: License :: OSI Approved :: GNU Lesser General Public License v3 or later (LGPLv3+)
Classifier: Programming Language :: Python
Classifier: Programming Language :: Python :: 3
Classifier: Programming Language :: Python :: 3.5
Classifier: Programming Language :: Python :: 3.6
Classifier: Programming Language :: Python :: Implementation :: CPython
